{"id":1170,"type":"analogous-triad","hues":[210,265,320],"saturations":[95,75,55,35],"lightnesses":[60,40,20],"color_group_length":6,"n":3,"colors":[{"hsl":[210,95,60],"rgb":[56,152,249],"hex":"#3898f9"},{"hsl":[210,95,40],"rgb":[5,101,198],"hex":"#0565c6"},{"hsl":[210,95,20],"rgb":[2,50,99],"hex":"#023263"},{"hsl":[210,75,60],"rgb":[76,152,229],"hex":"#4c98e5"},{"hsl":[210,75,40],"rgb":[25,101,178],"hex":"#1965b2"},{"hsl":[210,75,20],"rgb":[12,50,89],"hex":"#0c3259"},{"hsl":[210,55,60],"rgb":[96,152,209],"hex":"#6098d1"},{"hsl":[210,55,40],"rgb":[45,101,158],"hex":"#2d659e"},{"hsl":[210,55,20],"rgb":[22,50,79],"hex":"#16324f"},{"hsl":[210,35,60],"rgb":[117,152,188],"hex":"#7598bc"},{"hsl":[210,35,40],"rgb":[66,101,137],"hex":"#426589"},{"hsl":[210,35,20],"rgb":[33,50,68],"hex":"#213244"},{"hsl":[265,95,60],"rgb":[136,56,249],"hex":"#8838f9"},{"hsl":[265,95,40],"rgb":[85,5,198],"hex":"#5505c6"},{"hsl":[265,95,20],"rgb":[42,2,99],"hex":"#2a0263"},{"hsl":[265,75,60],"rgb":[140,76,229],"hex":"#8c4ce5"},{"hsl":[265,75,40],"rgb":[89,25,178],"hex":"#5919b2"},{"hsl":[265,75,20],"rgb":[44,12,89],"hex":"#2c0c59"},{"hsl":[265,55,60],"rgb":[143,96,209],"hex":"#8f60d1"},{"hsl":[265,55,40],"rgb":[92,45,158],"hex":"#5c2d9e"},{"hsl":[265,55,20],"rgb":[46,22,79],"hex":"#2e164f"},{"hsl":[265,35,60],"rgb":[147,117,188],"hex":"#9375bc"},{"hsl":[265,35,40],"rgb":[96,66,137],"hex":"#604289"},{"hsl":[265,35,20],"rgb":[48,33,68],"hex":"#302144"},{"hsl":[320,95,60],"rgb":[249,56,185],"hex":"#f938b9"},{"hsl":[320,95,40],"rgb":[198,5,134],"hex":"#c60586"},{"hsl":[320,95,20],"rgb":[99,2,67],"hex":"#630243"},{"hsl":[320,75,60],"rgb":[229,76,178],"hex":"#e54cb2"},{"hsl":[320,75,40],"rgb":[178,25,127],"hex":"#b2197f"},{"hsl":[320,75,20],"rgb":[89,12,63],"hex":"#590c3f"},{"hsl":[320,55,60],"rgb":[209,96,171],"hex":"#d160ab"},{"hsl":[320,55,40],"rgb":[158,45,120],"hex":"#9e2d78"},{"hsl":[320,55,20],"rgb":[79,22,60],"hex":"#4f163c"},{"hsl":[320,35,60],"rgb":[188,117,164],"hex":"#bc75a4"},{"hsl":[320,35,40],"rgb":[137,66,113],"hex":"#894271"},{"hsl":[320,35,20],"rgb":[68,33,56],"hex":"#442138"}]}