{"id":1247,"type":"analogous-quad","hues":[10,35,60,85],"saturations":[95,75,55,35],"lightnesses":[60,40,20],"color_group_length":6,"n":4,"colors":[{"hsl":[10,95,60],"rgb":[249,88,56],"hex":"#f95838"},{"hsl":[10,95,40],"rgb":[198,37,5],"hex":"#c62505"},{"hsl":[10,95,20],"rgb":[99,18,2],"hex":"#631202"},{"hsl":[10,75,60],"rgb":[229,101,76],"hex":"#e5654c"},{"hsl":[10,75,40],"rgb":[178,51,25],"hex":"#b23319"},{"hsl":[10,75,20],"rgb":[89,25,12],"hex":"#59190c"},{"hsl":[10,55,60],"rgb":[209,115,96],"hex":"#d17360"},{"hsl":[10,55,40],"rgb":[158,64,45],"hex":"#9e402d"},{"hsl":[10,55,20],"rgb":[79,32,22],"hex":"#4f2016"},{"hsl":[10,35,60],"rgb":[188,129,117],"hex":"#bc8175"},{"hsl":[10,35,40],"rgb":[137,78,66],"hex":"#894e42"},{"hsl":[10,35,20],"rgb":[68,39,33],"hex":"#442721"},{"hsl":[35,95,60],"rgb":[249,169,56],"hex":"#f9a938"},{"hsl":[35,95,40],"rgb":[198,118,5],"hex":"#c67605"},{"hsl":[35,95,20],"rgb":[99,59,2],"hex":"#633b02"},{"hsl":[35,75,60],"rgb":[229,165,76],"hex":"#e5a54c"},{"hsl":[35,75,40],"rgb":[178,114,25],"hex":"#b27219"},{"hsl":[35,75,20],"rgb":[89,57,12],"hex":"#59390c"},{"hsl":[35,55,60],"rgb":[209,162,96],"hex":"#d1a260"},{"hsl":[35,55,40],"rgb":[158,111,45],"hex":"#9e6f2d"},{"hsl":[35,55,20],"rgb":[79,55,22],"hex":"#4f3716"},{"hsl":[35,35,60],"rgb":[188,158,117],"hex":"#bc9e75"},{"hsl":[35,35,40],"rgb":[137,107,66],"hex":"#896b42"},{"hsl":[35,35,20],"rgb":[68,53,33],"hex":"#443521"},{"hsl":[60,95,60],"rgb":[249,249,56],"hex":"#f9f938"},{"hsl":[60,95,40],"rgb":[198,198,5],"hex":"#c6c605"},{"hsl":[60,95,20],"rgb":[99,99,2],"hex":"#636302"},{"hsl":[60,75,60],"rgb":[229,229,76],"hex":"#e5e54c"},{"hsl":[60,75,40],"rgb":[178,178,25],"hex":"#b2b219"},{"hsl":[60,75,20],"rgb":[89,89,12],"hex":"#59590c"},{"hsl":[60,55,60],"rgb":[209,209,96],"hex":"#d1d160"},{"hsl":[60,55,40],"rgb":[158,158,45],"hex":"#9e9e2d"},{"hsl":[60,55,20],"rgb":[79,79,22],"hex":"#4f4f16"},{"hsl":[60,35,60],"rgb":[188,188,117],"hex":"#bcbc75"},{"hsl":[60,35,40],"rgb":[137,137,66],"hex":"#898942"},{"hsl":[60,35,20],"rgb":[68,68,33],"hex":"#444421"},{"hsl":[85,95,60],"rgb":[169,249,56],"hex":"#a9f938"},{"hsl":[85,95,40],"rgb":[118,198,5],"hex":"#76c605"},{"hsl":[85,95,20],"rgb":[59,99,2],"hex":"#3b6302"},{"hsl":[85,75,60],"rgb":[165,229,76],"hex":"#a5e54c"},{"hsl":[85,75,40],"rgb":[114,178,25],"hex":"#72b219"},{"hsl":[85,75,20],"rgb":[57,89,12],"hex":"#39590c"},{"hsl":[85,55,60],"rgb":[162,209,96],"hex":"#a2d160"},{"hsl":[85,55,40],"rgb":[111,158,45],"hex":"#6f9e2d"},{"hsl":[85,55,20],"rgb":[55,79,22],"hex":"#374f16"},{"hsl":[85,35,60],"rgb":[158,188,117],"hex":"#9ebc75"},{"hsl":[85,35,40],"rgb":[107,137,66],"hex":"#6b8942"},{"hsl":[85,35,20],"rgb":[53,68,33],"hex":"#354421"}]}