{"id":194,"hues":[10,190],"saturations":[80,40],"lightnesses":[50,30,10],"color_group_length":6,"n":2,"colors":[{"hsl":[10,80,50],"rgb":[229,59,25],"hex":"#e53b19"},{"hsl":[10,80,30],"rgb":[137,35,15],"hex":"#89230f"},{"hsl":[10,80,10],"rgb":[45,11,5],"hex":"#2d0b05"},{"hsl":[10,40,50],"rgb":[178,93,76],"hex":"#b25d4c"},{"hsl":[10,40,30],"rgb":[107,56,45],"hex":"#6b382d"},{"hsl":[10,40,10],"rgb":[35,18,15],"hex":"#23120f"},{"hsl":[190,80,50],"rgb":[25,195,229],"hex":"#19c3e5"},{"hsl":[190,80,30],"rgb":[15,117,137],"hex":"#0f7589"},{"hsl":[190,80,10],"rgb":[5,39,45],"hex":"#05272d"},{"hsl":[190,40,50],"rgb":[76,161,178],"hex":"#4ca1b2"},{"hsl":[190,40,30],"rgb":[45,96,107],"hex":"#2d606b"},{"hsl":[190,40,10],"rgb":[15,32,35],"hex":"#0f2023"}],"type":"complementary"}