{"id":306,"hues":[120,300],"saturations":[90,50],"lightnesses":[50,30,10],"color_group_length":6,"n":2,"colors":[{"hsl":[120,90,50],"rgb":[12,242,12],"hex":"#0cf20c"},{"hsl":[120,90,30],"rgb":[7,145,7],"hex":"#079107"},{"hsl":[120,90,10],"rgb":[2,48,2],"hex":"#023002"},{"hsl":[120,50,50],"rgb":[63,191,63],"hex":"#3fbf3f"},{"hsl":[120,50,30],"rgb":[38,114,38],"hex":"#267226"},{"hsl":[120,50,10],"rgb":[12,38,12],"hex":"#0c260c"},{"hsl":[300,90,50],"rgb":[242,12,242],"hex":"#f20cf2"},{"hsl":[300,90,30],"rgb":[145,7,145],"hex":"#910791"},{"hsl":[300,90,10],"rgb":[48,2,48],"hex":"#300230"},{"hsl":[300,50,50],"rgb":[191,63,191],"hex":"#bf3fbf"},{"hsl":[300,50,30],"rgb":[114,38,114],"hex":"#722672"},{"hsl":[300,50,10],"rgb":[38,12,38],"hex":"#260c26"}],"type":"complementary"}