{"id":569,"hues":[80,170,260,350],"saturations":[95,65],"lightnesses":[60,40,20],"color_group_length":6,"n":4,"colors":[{"hsl":[80,95,60],"rgb":[185,249,56],"hex":"#b9f938"},{"hsl":[80,95,40],"rgb":[134,198,5],"hex":"#86c605"},{"hsl":[80,95,20],"rgb":[67,99,2],"hex":"#436302"},{"hsl":[80,65,60],"rgb":[175,219,86],"hex":"#afdb56"},{"hsl":[80,65,40],"rgb":[124,168,35],"hex":"#7ca823"},{"hsl":[80,65,20],"rgb":[62,84,17],"hex":"#3e5411"},{"hsl":[170,95,60],"rgb":[56,249,217],"hex":"#38f9d9"},{"hsl":[170,95,40],"rgb":[5,198,166],"hex":"#05c6a6"},{"hsl":[170,95,20],"rgb":[2,99,83],"hex":"#026353"},{"hsl":[170,65,60],"rgb":[86,219,197],"hex":"#56dbc5"},{"hsl":[170,65,40],"rgb":[35,168,146],"hex":"#23a892"},{"hsl":[170,65,20],"rgb":[17,84,73],"hex":"#115449"},{"hsl":[260,95,60],"rgb":[120,56,249],"hex":"#7838f9"},{"hsl":[260,95,40],"rgb":[69,5,198],"hex":"#4505c6"},{"hsl":[260,95,20],"rgb":[34,2,99],"hex":"#220263"},{"hsl":[260,65,60],"rgb":[130,86,219],"hex":"#8256db"},{"hsl":[260,65,40],"rgb":[79,35,168],"hex":"#4f23a8"},{"hsl":[260,65,20],"rgb":[39,17,84],"hex":"#271154"},{"hsl":[350,95,60],"rgb":[249,56,88],"hex":"#f93858"},{"hsl":[350,95,40],"rgb":[198,5,37],"hex":"#c60525"},{"hsl":[350,95,20],"rgb":[99,2,18],"hex":"#630212"},{"hsl":[350,65,60],"rgb":[219,86,108],"hex":"#db566c"},{"hsl":[350,65,40],"rgb":[168,35,57],"hex":"#a82339"},{"hsl":[350,65,20],"rgb":[84,17,28],"hex":"#54111c"}],"type":"tetradic"}