{"id":789,"type":"split-complementary","hues":[170,305,35],"saturations":[95,75,55,35],"lightnesses":[60,40,20],"color_group_length":6,"n":3,"colors":[{"hsl":[170,95,60],"rgb":[56,249,217],"hex":"#38f9d9"},{"hsl":[170,95,40],"rgb":[5,198,166],"hex":"#05c6a6"},{"hsl":[170,95,20],"rgb":[2,99,83],"hex":"#026353"},{"hsl":[170,75,60],"rgb":[76,229,204],"hex":"#4ce5cc"},{"hsl":[170,75,40],"rgb":[25,178,153],"hex":"#19b299"},{"hsl":[170,75,20],"rgb":[12,89,76],"hex":"#0c594c"},{"hsl":[170,55,60],"rgb":[96,209,190],"hex":"#60d1be"},{"hsl":[170,55,40],"rgb":[45,158,139],"hex":"#2d9e8b"},{"hsl":[170,55,20],"rgb":[22,79,69],"hex":"#164f45"},{"hsl":[170,35,60],"rgb":[117,188,176],"hex":"#75bcb0"},{"hsl":[170,35,40],"rgb":[66,137,125],"hex":"#42897d"},{"hsl":[170,35,20],"rgb":[33,68,62],"hex":"#21443e"},{"hsl":[305,95,60],"rgb":[249,56,233],"hex":"#f938e9"},{"hsl":[305,95,40],"rgb":[198,5,182],"hex":"#c605b6"},{"hsl":[305,95,20],"rgb":[99,2,91],"hex":"#63025b"},{"hsl":[305,75,60],"rgb":[229,76,216],"hex":"#e54cd8"},{"hsl":[305,75,40],"rgb":[178,25,165],"hex":"#b219a5"},{"hsl":[305,75,20],"rgb":[89,12,82],"hex":"#590c52"},{"hsl":[305,55,60],"rgb":[209,96,199],"hex":"#d160c7"},{"hsl":[305,55,40],"rgb":[158,45,148],"hex":"#9e2d94"},{"hsl":[305,55,20],"rgb":[79,22,74],"hex":"#4f164a"},{"hsl":[305,35,60],"rgb":[188,117,182],"hex":"#bc75b6"},{"hsl":[305,35,40],"rgb":[137,66,131],"hex":"#894283"},{"hsl":[305,35,20],"rgb":[68,33,65],"hex":"#442141"},{"hsl":[35,95,60],"rgb":[249,169,56],"hex":"#f9a938"},{"hsl":[35,95,40],"rgb":[198,118,5],"hex":"#c67605"},{"hsl":[35,95,20],"rgb":[99,59,2],"hex":"#633b02"},{"hsl":[35,75,60],"rgb":[229,165,76],"hex":"#e5a54c"},{"hsl":[35,75,40],"rgb":[178,114,25],"hex":"#b27219"},{"hsl":[35,75,20],"rgb":[89,57,12],"hex":"#59390c"},{"hsl":[35,55,60],"rgb":[209,162,96],"hex":"#d1a260"},{"hsl":[35,55,40],"rgb":[158,111,45],"hex":"#9e6f2d"},{"hsl":[35,55,20],"rgb":[79,55,22],"hex":"#4f3716"},{"hsl":[35,35,60],"rgb":[188,158,117],"hex":"#bc9e75"},{"hsl":[35,35,40],"rgb":[137,107,66],"hex":"#896b42"},{"hsl":[35,35,20],"rgb":[68,53,33],"hex":"#443521"}]}