{"id":853,"type":"split-complementary","hues":[300,85,155],"saturations":[95,75,55,35],"lightnesses":[60,40,20],"color_group_length":6,"n":3,"colors":[{"hsl":[300,95,60],"rgb":[249,56,249],"hex":"#f938f9"},{"hsl":[300,95,40],"rgb":[198,5,198],"hex":"#c605c6"},{"hsl":[300,95,20],"rgb":[99,2,99],"hex":"#630263"},{"hsl":[300,75,60],"rgb":[229,76,229],"hex":"#e54ce5"},{"hsl":[300,75,40],"rgb":[178,25,178],"hex":"#b219b2"},{"hsl":[300,75,20],"rgb":[89,12,89],"hex":"#590c59"},{"hsl":[300,55,60],"rgb":[209,96,209],"hex":"#d160d1"},{"hsl":[300,55,40],"rgb":[158,45,158],"hex":"#9e2d9e"},{"hsl":[300,55,20],"rgb":[79,22,79],"hex":"#4f164f"},{"hsl":[300,35,60],"rgb":[188,117,188],"hex":"#bc75bc"},{"hsl":[300,35,40],"rgb":[137,66,137],"hex":"#894289"},{"hsl":[300,35,20],"rgb":[68,33,68],"hex":"#442144"},{"hsl":[85,95,60],"rgb":[169,249,56],"hex":"#a9f938"},{"hsl":[85,95,40],"rgb":[118,198,5],"hex":"#76c605"},{"hsl":[85,95,20],"rgb":[59,99,2],"hex":"#3b6302"},{"hsl":[85,75,60],"rgb":[165,229,76],"hex":"#a5e54c"},{"hsl":[85,75,40],"rgb":[114,178,25],"hex":"#72b219"},{"hsl":[85,75,20],"rgb":[57,89,12],"hex":"#39590c"},{"hsl":[85,55,60],"rgb":[162,209,96],"hex":"#a2d160"},{"hsl":[85,55,40],"rgb":[111,158,45],"hex":"#6f9e2d"},{"hsl":[85,55,20],"rgb":[55,79,22],"hex":"#374f16"},{"hsl":[85,35,60],"rgb":[158,188,117],"hex":"#9ebc75"},{"hsl":[85,35,40],"rgb":[107,137,66],"hex":"#6b8942"},{"hsl":[85,35,20],"rgb":[53,68,33],"hex":"#354421"},{"hsl":[155,95,60],"rgb":[56,249,169],"hex":"#38f9a9"},{"hsl":[155,95,40],"rgb":[5,198,118],"hex":"#05c676"},{"hsl":[155,95,20],"rgb":[2,99,59],"hex":"#02633b"},{"hsl":[155,75,60],"rgb":[76,229,165],"hex":"#4ce5a5"},{"hsl":[155,75,40],"rgb":[25,178,114],"hex":"#19b272"},{"hsl":[155,75,20],"rgb":[12,89,57],"hex":"#0c5939"},{"hsl":[155,55,60],"rgb":[96,209,162],"hex":"#60d1a2"},{"hsl":[155,55,40],"rgb":[45,158,111],"hex":"#2d9e6f"},{"hsl":[155,55,20],"rgb":[22,79,55],"hex":"#164f37"},{"hsl":[155,35,60],"rgb":[117,188,158],"hex":"#75bc9e"},{"hsl":[155,35,40],"rgb":[66,137,107],"hex":"#42896b"},{"hsl":[155,35,20],"rgb":[33,68,53],"hex":"#214435"}]}